<?xml version="1.0" encoding="utf-8"?>
<clothing-items>
 <clothing>
  <id>
   917984953
  </id>
  <name>
   Lacoste Jacket A-5061
  </name>
  <category>
   Jacket
  </category>
  <size>
   M
  </size>
  <color>
   Зеленый
  </color>
  <material>
   Хлопок
  </material>
  <price>
   662032
  </price>
  <rating>
   2.08
  </rating>
  <reviews>
   724328
  </reviews>
 </clothing>
 <clothing>
  <id>
   861168971
  </id>
  <name>
   Nike Belts M-4379
  </name>
  <category>
   Belts
  </category>
  <size>
   S
  </size>
  <color>
   Оранжевый
  </color>
  <material>
   Полиэстер
  </material>
  <price>
   117090
  </price>
  <rating>
   3.65
  </rating>
  <reviews>
   623759
  </reviews>
  <new>
   -
  </new>
  <exclusive>
   yes
  </exclusive>
  <sporty>
   no
  </sporty>
 </clothing>
 <clothing>
  <id>
   646288733
  </id>
  <name>
   Reebok Belts X-3356
  </name>
  <category>
   Belts
  </category>
  <size>
   XL
  </size>
  <color>
   Желтый
  </color>
  <material>
   Шелк
  </material>
  <price>
   875762
  </price>
  <rating>
   1.58
  </rating>
  <reviews>
   604406
  </reviews>
  <exclusive>
   no
  </exclusive>
 </clothing>
 <clothing>
  <id>
   697554522
  </id>
  <name>
   New Balance Belts T-4133
  </name>
  <category>
   Belts
  </category>
  <size>
   S
  </size>
  <color>
   Оранжевый
  </color>
  <material>
   Полиэстер
  </material>
  <price>
   107252
  </price>
  <rating>
   3.23
  </rating>
  <reviews>
   491101
  </reviews>
  <new>
   -
  </new>
  <sporty>
   yes
  </sporty>
 </clothing>
 <clothing>
  <id>
   238431269
  </id>
  <name>
   Under Armour Pants R-4869
  </name>
  <category>
   Pants
  </category>
  <size>
   S
  </size>
  <color>
   Желтый
  </color>
  <material>
   Полиэстер
  </material>
  <price>
   661313
  </price>
  <rating>
   2.33
  </rating>
  <reviews>
   806718
  </reviews>
  <exclusive>
   no
  </exclusive>
 </clothing>
 <clothing>
  <id>
   177075532
  </id>
  <name>
   Brooks Belts H-3609
  </name>
  <category>
   Belts
  </category>
  <size>
   L
  </size>
  <color>
   Оранжевый
  </color>
  <material>
   Хлопок
  </material>
  <price>
   157096
  </price>
  <rating>
   3.79
  </rating>
  <reviews>
   444190
  </reviews>
  <new>
   -
  </new>
  <exclusive>
   no
  </exclusive>
 </clothing>
 <clothing>
  <id>
   373438455
  </id>
  <name>
   Under Armour Shoes F-9318
  </name>
  <category>
   Shoes
  </category>
  <size>
   S
  </size>
  <color>
   Оранжевый
  </color>
  <material>
   Хлопок
  </material>
  <price>
   584190
  </price>
  <rating>
   2.48
  </rating>
  <reviews>
   223376
  </reviews>
  <new>
   -
  </new>
  <exclusive>
   yes
  </exclusive>
  <sporty>
   yes
  </sporty>
 </clothing>
 <clothing>
  <id>
   827104813
  </id>
  <name>
   Reebok Shoes H-5189
  </name>
  <category>
   Shoes
  </category>
  <size>
   XXL
  </size>
  <color>
   Желтый
  </color>
  <material>
   Шелк
  </material>
  <price>
   627342
  </price>
  <rating>
   3.15
  </rating>
  <reviews>
   325298
  </reviews>
  <new>
   -
  </new>
  <exclusive>
   yes
  </exclusive>
  <sporty>
   yes
  </sporty>
 </clothing>
 <clothing>
  <id>
   460062780
  </id>
  <name>
   Asics Socks Z-8099
  </name>
  <category>
   Socks
  </category>
  <size>
   XL
  </size>
  <color>
   Оранжевый
  </color>
  <material>
   Вискоза
  </material>
  <price>
   797236
  </price>
  <rating>
   2.73
  </rating>
  <reviews>
   414262
  </reviews>
  <exclusive>
   no
  </exclusive>
 </clothing>
 <clothing>
  <id>
   561563376
  </id>
  <name>
   Asics T-shirt X-4786
  </name>
  <category>
   T-shirt
  </category>
  <size>
   XL
  </size>
  <color>
   Синий
  </color>
  <material>
   Шерсть
  </material>
  <price>
   720510
  </price>
  <rating>
   1.49
  </rating>
  <reviews>
   911056
  </reviews>
  <new>
   -
  </new>
  <exclusive>
   yes
  </exclusive>
  <sporty>
   no
  </sporty>
 </clothing>
 <clothing>
  <id>
   359509316
  </id>
  <name>
   Asics Sweater K-8397
  </name>
  <category>
   Sweater
  </category>
  <size>
   M
  </size>
  <color>
   Оранжевый
  </color>
  <material>
   Кожа
  </material>
  <price>
   490637
  </price>
  <rating>
   4.76
  </rating>
  <reviews>
   210287
  </reviews>
  <new>
   +
  </new>
  <exclusive>
   no
  </exclusive>
 </clothing>
 <clothing>
  <id>
   179250030
  </id>
  <name>
   Ellesse Belts G-6860
  </name>
  <category>
   Belts
  </category>
  <size>
   XL
  </size>
  <color>
   Голубой
  </color>
  <material>
   Нейлон
  </material>
  <price>
   337359
  </price>
  <rating>
   1.38
  </rating>
  <reviews>
   544855
  </reviews>
  <new>
   -
  </new>
 </clothing>
 <clothing>
  <id>
   780793496
  </id>
  <name>
   Adidas Umbrellas X-5516
  </name>
  <category>
   Umbrellas
  </category>
  <size>
   XL
  </size>
  <color>
   Желтый
  </color>
  <material>
   Шелк
  </material>
  <price>
   187675
  </price>
  <rating>
   3.04
  </rating>
  <reviews>
   481424
  </reviews>
  <new>
   -
  </new>
  <exclusive>
   no
  </exclusive>
  <sporty>
   yes
  </sporty>
 </clothing>
 <clothing>
  <id>
   947943204
  </id>
  <name>
   Puma Dress Y-3635
  </name>
  <category>
   Dress
  </category>
  <size>
   XXL
  </size>
  <color>
   Синий
  </color>
  <material>
   Кожа
  </material>
  <price>
   135578
  </price>
  <rating>
   2.68
  </rating>
  <reviews>
   236334
  </reviews>
  <new>
   +
  </new>
  <exclusive>
   no
  </exclusive>
 </clothing>
 <clothing>
  <id>
   453847816
  </id>
  <name>
   Reebok Hat M-7863
  </name>
  <category>
   Hat
  </category>
  <size>
   M
  </size>
  <color>
   Оранжевый
  </color>
  <material>
   Шерсть
  </material>
  <price>
   934329
  </price>
  <rating>
   3.63
  </rating>
  <reviews>
   283099
  </reviews>
  <new>
   +
  </new>
 </clothing>
 <clothing>
  <id>
   633617122
  </id>
  <name>
   Puma Skirt U-7886
  </name>
  <category>
   Skirt
  </category>
  <size>
   XXL
  </size>
  <color>
   Красный
  </color>
  <material>
   Вискоза
  </material>
  <price>
   833141
  </price>
  <rating>
   2.97
  </rating>
  <reviews>
   150349
  </reviews>
  <new>
   -
  </new>
  <exclusive>
   no
  </exclusive>
  <sporty>
   yes
  </sporty>
 </clothing>
 <clothing>
  <id>
   499860855
  </id>
  <name>
   Nike Blouse A-5663
  </name>
  <category>
   Blouse
  </category>
  <size>
   L
  </size>
  <color>
   Синий
  </color>
  <material>
   Полиэстер
  </material>
  <price>
   958463
  </price>
  <rating>
   3.69
  </rating>
  <reviews>
   68416
  </reviews>
  <new>
   +
  </new>
  <exclusive>
   no
  </exclusive>
  <sporty>
   no
  </sporty>
 </clothing>
 <clothing>
  <id>
   505177532
  </id>
  <name>
   Asics Skirt Q-7521
  </name>
  <category>
   Skirt
  </category>
  <size>
   S
  </size>
  <color>
   Красный
  </color>
  <material>
   Вискоза
  </material>
  <price>
   423228
  </price>
  <rating>
   1.91
  </rating>
  <reviews>
   900691
  </reviews>
  <new>
   +
  </new>
 </clothing>
 <clothing>
  <id>
   101642730
  </id>
  <name>
   Puma Socks B-6965
  </name>
  <category>
   Socks
  </category>
  <size>
   L
  </size>
  <color>
   Красный
  </color>
  <material>
   Лен
  </material>
  <price>
   100602
  </price>
  <rating>
   2.73
  </rating>
  <reviews>
   535433
  </reviews>
  <new>
   -
  </new>
  <exclusive>
   no
  </exclusive>
  <sporty>
   no
  </sporty>
 </clothing>
 <clothing>
  <id>
   210838821
  </id>
  <name>
   Adidas Skirt J-5082
  </name>
  <category>
   Skirt
  </category>
  <size>
   S
  </size>
  <color>
   Зеленый
  </color>
  <material>
   Вискоза
  </material>
  <price>
   785301
  </price>
  <rating>
   4.6
  </rating>
  <reviews>
   939333
  </reviews>
  <new>
   -
  </new>
  <exclusive>
   no
  </exclusive>
  <sporty>
   yes
  </sporty>
 </clothing>
 <clothing>
  <id>
   867324073
  </id>
  <name>
   New Balance Shirt M-5163
  </name>
  <category>
   Shirt
  </category>
  <size>
   XL
  </size>
  <color>
   Фиолетовый
  </color>
  <material>
   Вискоза
  </material>
  <price>
   930246
  </price>
  <rating>
   3.96
  </rating>
  <reviews>
   41143
  </reviews>
  <new>
   -
  </new>
  <exclusive>
   no
  </exclusive>
  <sporty>
   yes
  </sporty>
 </clothing>
 <clothing>
  <id>
   290331765
  </id>
  <name>
   Reebok Hat A-2990
  </name>
  <category>
   Hat
  </category>
  <size>
   XL
  </size>
  <color>
   Желтый
  </color>
  <material>
   Вискоза
  </material>
  <price>
   463555
  </price>
  <rating>
   1.89
  </rating>
  <reviews>
   452734
  </reviews>
  <new>
   +
  </new>
  <exclusive>
   no
  </exclusive>
  <sporty>
   yes
  </sporty>
 </clothing>
 <clothing>
  <id>
   663008305
  </id>
  <name>
   Puma Socks Z-4908
  </name>
  <category>
   Socks
  </category>
  <size>
   XXL
  </size>
  <color>
   Красный
  </color>
  <material>
   Шерсть
  </material>
  <price>
   579110
  </price>
  <rating>
   3.02
  </rating>
  <reviews>
   306837
  </reviews>
  <exclusive>
   yes
  </exclusive>
 </clothing>
 <clothing>
  <id>
   376384158
  </id>
  <name>
   Brooks Gloves X-8723
  </name>
  <category>
   Gloves
  </category>
  <size>
   XL
  </size>
  <color>
   Синий
  </color>
  <material>
   Полиэстер
  </material>
  <price>
   183973
  </price>
  <rating>
   3.52
  </rating>
  <reviews>
   307496
  </reviews>
  <exclusive>
   yes
  </exclusive>
 </clothing>
</clothing-items>
