<?xml version="1.0" encoding="utf-8"?>
<clothing-items>
 <clothing>
  <id>
   858090078
  </id>
  <name>
   Converse Handbags B-9090
  </name>
  <category>
   Handbags
  </category>
  <size>
   S
  </size>
  <color>
   Оранжевый
  </color>
  <material>
   Полиэстер
  </material>
  <price>
   850217
  </price>
  <rating>
   3.46
  </rating>
  <reviews>
   790352
  </reviews>
  <exclusive>
   no
  </exclusive>
  <sporty>
   yes
  </sporty>
 </clothing>
 <clothing>
  <id>
   958514198
  </id>
  <name>
   Addidas Gloves T-3875
  </name>
  <category>
   Gloves
  </category>
  <size>
   XL
  </size>
  <color>
   Оранжевый
  </color>
  <material>
   Кожа
  </material>
  <price>
   381435
  </price>
  <rating>
   2.29
  </rating>
  <reviews>
   341994
  </reviews>
  <new>
   -
  </new>
  <exclusive>
   yes
  </exclusive>
  <sporty>
   no
  </sporty>
 </clothing>
 <clothing>
  <id>
   283905955
  </id>
  <name>
   Fila Shoes I-2731
  </name>
  <category>
   Shoes
  </category>
  <size>
   L
  </size>
  <color>
   Красный
  </color>
  <material>
   Шелк
  </material>
  <price>
   786694
  </price>
  <rating>
   3.48
  </rating>
  <reviews>
   765235
  </reviews>
  <new>
   -
  </new>
  <exclusive>
   yes
  </exclusive>
  <sporty>
   yes
  </sporty>
 </clothing>
 <clothing>
  <id>
   485380228
  </id>
  <name>
   Under Armour Skirt N-3695
  </name>
  <category>
   Skirt
  </category>
  <size>
   M
  </size>
  <color>
   Красный
  </color>
  <material>
   Шерсть
  </material>
  <price>
   531801
  </price>
  <rating>
   3.59
  </rating>
  <reviews>
   762888
  </reviews>
  <new>
   -
  </new>
  <sporty>
   no
  </sporty>
 </clothing>
 <clothing>
  <id>
   906168348
  </id>
  <name>
   Vans Umbrellas Y-1337
  </name>
  <category>
   Umbrellas
  </category>
  <size>
   XL
  </size>
  <color>
   Синий
  </color>
  <material>
   Хлопок
  </material>
  <price>
   874887
  </price>
  <rating>
   3.22
  </rating>
  <reviews>
   473082
  </reviews>
  <new>
   -
  </new>
 </clothing>
 <clothing>
  <id>
   904532578
  </id>
  <name>
   Brooks Belts O-9492
  </name>
  <category>
   Belts
  </category>
  <size>
   M
  </size>
  <color>
   Голубой
  </color>
  <material>
   Кожа
  </material>
  <price>
   250248
  </price>
  <rating>
   2.46
  </rating>
  <reviews>
   154551
  </reviews>
  <new>
   -
  </new>
 </clothing>
 <clothing>
  <id>
   497441851
  </id>
  <name>
   Addidas Skirt S-5370
  </name>
  <category>
   Skirt
  </category>
  <size>
   XL
  </size>
  <color>
   Голубой
  </color>
  <material>
   Лен
  </material>
  <price>
   316514
  </price>
  <rating>
   2.64
  </rating>
  <reviews>
   676800
  </reviews>
  <new>
   -
  </new>
  <exclusive>
   no
  </exclusive>
  <sporty>
   no
  </sporty>
 </clothing>
 <clothing>
  <id>
   553250306
  </id>
  <name>
   Vans Sweater Q-3533
  </name>
  <category>
   Sweater
  </category>
  <size>
   L
  </size>
  <color>
   Голубой
  </color>
  <material>
   Хлопок
  </material>
  <price>
   783424
  </price>
  <rating>
   3.39
  </rating>
  <reviews>
   626375
  </reviews>
  <new>
   +
  </new>
  <exclusive>
   yes
  </exclusive>
 </clothing>
 <clothing>
  <id>
   608474919
  </id>
  <name>
   Vans Hat A-8926
  </name>
  <category>
   Hat
  </category>
  <size>
   XXL
  </size>
  <color>
   Фиолетовый
  </color>
  <material>
   Нейлон
  </material>
  <price>
   944836
  </price>
  <rating>
   1.4
  </rating>
  <reviews>
   747728
  </reviews>
  <new>
   -
  </new>
  <exclusive>
   no
  </exclusive>
 </clothing>
 <clothing>
  <id>
   825097438
  </id>
  <name>
   Asics Dress U-7300
  </name>
  <category>
   Dress
  </category>
  <size>
   XL
  </size>
  <color>
   Голубой
  </color>
  <material>
   Кожа
  </material>
  <price>
   846734
  </price>
  <rating>
   3.76
  </rating>
  <reviews>
   986067
  </reviews>
  <new>
   +
  </new>
  <exclusive>
   no
  </exclusive>
  <sporty>
   no
  </sporty>
 </clothing>
 <clothing>
  <id>
   984270472
  </id>
  <name>
   PleinSport Skirt C-3756
  </name>
  <category>
   Skirt
  </category>
  <size>
   S
  </size>
  <color>
   Оранжевый
  </color>
  <material>
   Шелк
  </material>
  <price>
   584307
  </price>
  <rating>
   1.2
  </rating>
  <reviews>
   3552
  </reviews>
  <new>
   +
  </new>
  <sporty>
   yes
  </sporty>
 </clothing>
 <clothing>
  <id>
   289258857
  </id>
  <name>
   Reebok Shirt Y-7519
  </name>
  <category>
   Shirt
  </category>
  <size>
   M
  </size>
  <color>
   Оранжевый
  </color>
  <material>
   Шелк
  </material>
  <price>
   981469
  </price>
  <rating>
   1.34
  </rating>
  <reviews>
   468370
  </reviews>
  <new>
   -
  </new>
  <exclusive>
   no
  </exclusive>
  <sporty>
   no
  </sporty>
 </clothing>
 <clothing>
  <id>
   716352290
  </id>
  <name>
   Brooks Jacket E-5794
  </name>
  <category>
   Jacket
  </category>
  <size>
   S
  </size>
  <color>
   Фиолетовый
  </color>
  <material>
   Шелк
  </material>
  <price>
   619676
  </price>
  <rating>
   2.83
  </rating>
  <reviews>
   855960
  </reviews>
  <sporty>
   yes
  </sporty>
 </clothing>
</clothing-items>
